data_agent_aspen_ip21/__init__.py
data_agent_aspen_ip21/connector.py
data_agent_aspen_ip21-0.2.5.dist-info/licenses/LICENSE.txt
data_agent_aspen_ip21-0.2.5.dist-info/METADATA
data_agent_aspen_ip21-0.2.5.dist-info/WHEEL
data_agent_aspen_ip21-0.2.5.dist-info/entry_points.txt
data_agent_aspen_ip21-0.2.5.dist-info/top_level.txt
data_agent_aspen_ip21-0.2.5.dist-info/RECORD
