Metadata-Version: 2.4
Name: data-agent-aspen-ip21
Version: 0.2.5
Summary: Aspen IP21 historian plugin for `data-agent` package
Home-page: https://github.com/imubit/data-agent-aspen-ip21/
Author: Meir Tseitlin
License: LGPL-3.0-only
Project-URL: Documentation, https://github.com/imubit/data-agent-aspen-ip21/
Project-URL: Source, https://github.com/imubit/data-agent-aspen-ip21/
Platform: any
Classifier: Development Status :: 4 - Beta
Classifier: Programming Language :: Python
License-File: LICENSE.txt
Requires-Dist: importlib-metadata; python_version < "3.8"
Requires-Dist: pyodbc
Requires-Dist: pandas
Requires-Dist: pypika
Requires-Dist: data-agent
Provides-Extra: testing
Requires-Dist: setuptools; extra == "testing"
Requires-Dist: pytest; extra == "testing"
Requires-Dist: pytest-cov; extra == "testing"
Dynamic: license-file
